eventlet_promise/__init__.py
eventlet_promise/promise.py
eventlet_promise/promise_js.py
eventlet_promise/thenable.py
eventlet_promise/utils.py
eventlet_promise-0.5.1.dist-info/METADATA
eventlet_promise-0.5.1.dist-info/WHEEL
eventlet_promise-0.5.1.dist-info/licenses/LICENSE
eventlet_promise-0.5.1.dist-info/RECORD
