Metadata-Version: 2.1
Name: eventlet_promise
Version: 0.5.1
Summary: Implementing Javascript-like async Promise in Python for Eventlet-based coroutines.
Project-URL: Homepage, https://github.com/htanwar922/eventlet-promise
Project-URL: Bug Tracker, https://github.com/htanwar922/eventlet-promise/issues
Author-email: Himanshu <htanwar922@gmail.com>
License-File: LICENSE
Classifier: License :: OSI Approved :: MIT License
Classifier: Operating System :: OS Independent
Classifier: Programming Language :: Python :: 3
Requires-Python: >=3.7
